cookiecutterassert/__init__.py
cookiecutterassert/assertion_file_parser.py
cookiecutterassert/cookie_cutter_interface.py
cookiecutterassert/folder_scanner.py
cookiecutterassert/main.py
cookiecutterassert/messager.py
cookiecutterassert/options_parser.py
cookiecutterassert/stale_test_folder_cleanup.py
cookiecutterassert/test_coordinator.py
cookiecutterassert/test_folder_executor.py
cookiecutterassert/rules/__init__.py
cookiecutterassert/rules/file_contains_line.py
cookiecutterassert/rules/file_contains_snippet_rule.py
cookiecutterassert/rules/file_does_not_contain_line.py
cookiecutterassert/rules/file_does_not_contain_snippet.py
cookiecutterassert/rules/file_does_not_regex_match.py
cookiecutterassert/rules/file_has_regex_match_line.py
cookiecutterassert/rules/file_matches.py
cookiecutterassert/rules/option_names.py
cookiecutterassert/rules/path_exists.py
cookiecutterassert/rules/path_not_exists.py
cookiecutterassert/rules/rules_util.py
cookiecutterassert/rules/run_script.py
cookiecutterassert-2.0.0.dist-info/LICENSE.txt
cookiecutterassert-2.0.0.dist-info/METADATA
cookiecutterassert-2.0.0.dist-info/WHEEL
cookiecutterassert-2.0.0.dist-info/entry_points.txt
cookiecutterassert-2.0.0.dist-info/top_level.txt
cookiecutterassert-2.0.0.dist-info/RECORD
