Metadata-Version: 2.1
Name: cookiecutterassert
Version: 2.0.0
Summary: Automated testing framework for python cookie cutter
Home-page: https://github.com/cookiecutterassert/cookiecutterassert
Author: Micah Tessler
Author-email: mtessler@ford.com
License: Apache Software License
Platform: UNKNOWN
Classifier: Programming Language :: Python :: 3
Classifier: Operating System :: OS Independent
Classifier: License :: OSI Approved :: Apache Software License
Requires-Python: >=3.8
License-File: LICENSE.txt
Requires-Dist: click
Requires-Dist: cookiecutter
Requires-Dist: pyyaml
